hlp/__init__.py
hlp/cli.py
hlp/compat.py
hlp/typing.py
hlp/util.py
hlp-0.2.1.dist-info/LICENSE.txt
hlp-0.2.1.dist-info/METADATA
hlp-0.2.1.dist-info/WHEEL
hlp-0.2.1.dist-info/entry_points.txt
hlp-0.2.1.dist-info/top_level.txt
hlp-0.2.1.dist-info/RECORD
