Metadata-Version: 2.1
Name: hlp
Version: 0.2.1
Summary: Python help CLI
Home-page: https://github.com/chrahunt/hlp
Author: Chris Hunt
Author-email: chrahunt@gmail.com
License: MIT
Keywords: help,cli,command
Platform: UNKNOWN
Classifier: Development Status :: 3 - Alpha
Classifier: Environment :: Console
Classifier: Intended Audience :: Developers
Classifier: License :: OSI Approved :: MIT License
Classifier: Programming Language :: Python :: 2.7
Classifier: Programming Language :: Python :: 3
Classifier: Topic :: Software Development :: Documentation
Requires-Python: >=2.7
